Workbook

Sheet Instructions
A1: THE FOUNDER'S SPRINT
A2: 12-Month Financial Model Template
A4: HOW TO USE THIS TEMPLATE
A5: 1. Go to the Assumptions tab and fill in your business details (all blue cells are editable).
A6: 2. Start with your estimated first-month revenue and expected monthly growth rate.
A7: 3. Enter your COGS percentage — what it costs to produce/deliver your product or service.
A8: 4. Fill in your monthly operating expenses — rent, salaries, marketing, etc.
A9: 5. The P&L tab will automatically calculate your monthly and annual profit/loss.
A10: 6. The Cash Flow tab shows your running cash position month by month.
A11: 7. Adjust assumptions to model different scenarios (optimistic, realistic, pessimistic).
A13: COLOUR GUIDE
A14: Blue text = editable inputs (change these)
... A24: If VAT-registered, model revenue net of VAT (18%).

Sheet Assumptions
A1: THE FOUNDER'S SPRINT — FINANCIAL MODEL
A2: Key Assumptions (edit blue cells)
A4: Company Name | B4: Your Startup Name
A5: Currency | B5: UGX
A6: Fiscal Year Start | B6: 2026
A8: REVENUE ASSUMPTIONS
A9: Starting Monthly Revenue (UGX) | B9: 500000
A10: Monthly Revenue Growth Rate | B10: 0.1
A11: Average Unit Price (UGX) | B11: 25000
A13: COST OF GOODS SOLD (COGS)
A14: COGS as % of Revenue | B14: 0.35
A16: OPERATING EXPENSES
A17: Rent / Office | B17: 300000
A18: Salaries & Wages | B18: 1500000
A19: Marketing & Advertising | B19: 200000
A20: Utilities (Power, Internet, Water) | B20: 150000
A21: Transport & Logistics | B21: 100000
A22: Professional Services (Legal, Accounting) | B22: 100000
A23: Software & Tools | B23: 50000
A24: Insurance | B24: 50000
A25: Miscellaneous | B25: 75000
A27: GROWTH ASSUMPTIONS
A28: OpEx Annual Increase | B28: 0.05
A30: Note: All blue cells are editable inputs. Change them to model your business.

Sheet P&L
A1: 12-MONTH PROFIT & LOSS PROJECTION
B3: Jan | C3: Feb | D3: Mar | E3: Apr | F3: May | G3: Jun | H3: Jul | I3: Aug | J3: Sep | K3: Oct | L3: Nov | M3: Dec | N3: TOTAL
A5: REVENUE
A6: Monthly Revenue | B6: =Assumptions!B9 | C6: =B6*(1+Assumptions!B10) | D6: =C6*(1+Assumptions!B10) | E6: =D6*(1+Assumptions!B10) | F6: =E6*(1+Assumptions!B10) | G6: =F6*(1+Assumptions!B10) | H6: =G6*(1+Assumptions!B10) | I6: =H6*(1+Assumptions!B10) | J6: =I6*(1+Assumptions!B10) | K6: =J6*(1+Assumptions!B10) | L6: =K6*(1+Assumptions!B10) | M6: =L6*(1+Assumptions!B10) | N6: =SUM(B6:M6)
A8: COST OF GOODS SOLD
A9: COGS | B9: =-B6*Assumptions!B14 | C9: =-C6*Assumptions!B14 | D9: =-D6*Assumptions!B14 | E9: =-E6*Assumptions!B14 | F9: =-F6*Assumptions!B14 | G9: =-G6*Assumptions!B14 | H9: =-H6*Assumptions!B14 | I9: =-I6*Assumptions!B14 | J9: =-J6*Assumptions!B14 | K9: =-K6*Assumptions!B14 | L9: =-L6*Assumptions!B14 | M9: =-M6*Assumptions!B14 | N9: =SUM(B9:M9)
A11: GROSS PROFIT | B11: =B6+B9 | C11: =C6+C9 | D11: =D6+D9 | E11: =E6+E9 | F11: =F6+F9 | G11: =G6+G9 | H11: =H6+H9 | I11: =I6+I9 | ... M11: =M6+M9 | N11: =SUM(B11:M11)
A12: Gross Margin % | B12: =IF(B6=0,0,B11/B6) | C12: =IF(C6=0,0,C11/C6) | D12: =IF(D6=0,0,D11/D6) | E12: =IF(E6=0,0,E11/E6) | F12: =IF(F6=0,0,F11/F6) | G12: =IF(G6=0,0,G11/G6) | H12: =IF(H6=0,0,H11/H6) | I12: =IF(I6=0,0,I11/I6) | ... M12: =IF(M6=0,0,M11/M6)
A14: OPERATING EXPENSES
A15: Rent / Office | B15: =-Assumptions!B17 | C15: =-Assumptions!B17 | D15: =-Assumptions!B17 | E15: =-Assumptions!B17 | F15: =-Assumptions!B17 | G15: =-Assumptions!B17 | H15: =-Assumptions!B17 | I15: =-Assumptions!B17 | J15: =-Assumptions!B17 | K15: =-Assumptions!B17 | L15: =-Assumptions!B17 | M15: =-Assumptions!B17 | N15: =SUM(B15:M15)
A16: Salaries & Wages | B16: =-Assumptions!B18 | C16: =-Assumptions!B18 | D16: =-Assumptions!B18 | E16: =-Assumptions!B18 | F16: =-Assumptions!B18 | G16: =-Assumptions!B18 | H16: =-Assumptions!B18 | I16: =-Assumptions!B18 | J16: =-Assumptions!B18 | K16: =-Assumptions!B18 | L16: =-Assumptions!B18 | M16: =-Assumptions!B18 | N16: =SUM(B16:M16)
A17: Marketing & Advertising | B17: =-Assumptions!B19 | C17: =-Assumptions!B19 | D17: =-Assumptions!B19 | E17: =-Assumptions!B19 | F17: =-Assumptions!B19 | G17: =-Assumptions!B19 | H17: =-Assumptions!B19 | I17: =-Assumptions!B19 | J17: =-Assumptions!B19 | K17: =-Assumptions!B19 | L17: =-Assumptions!B19 | M17: =-Assumptions!B19 | N17: =SUM(B17:M17)
A18: Utilities (Power, Internet, Water) | B18: =-Assumptions!B20 | C18: =-Assumptions!B20 | D18: =-Assumptions!B20 | E18: =-Assumptions!B20 | F18: =-Assumptions!B20 | G18: =-Assumptions!B20 | H18: =-Assumptions!B20 | I18: =-Assumptions!B20 | J18: =-Assumptions!B20 | K18: =-Assumptions!B20 | L18: =-Assumptions!B20 | M18: =-Assumptions!B20 | N18: =SUM(B18:M18)
A19: Transport & Logistics | B19: =-Assumptions!B21 | C19: =-Assumptions!B21 | D19: =-Assumptions!B21 | E19: =-Assumptions!B21 | F19: =-Assumptions!B21 | G19: =-Assumptions!B21 | H19: =-Assumptions!B21 | I19: =-Assumptions!B21 | J19: =-Assumptions!B21 | K19: =-Assumptions!B21 | L19: =-Assumptions!B21 | M19: =-Assumptions!B21 | N19: =SUM(B19:M19)
A20: Professional Services (Legal, Accounting) | B20: =-Assumptions!B22 | C20: =-Assumptions!B22 | D20: =-Assumptions!B22 | E20: =-Assumptions!B22 | F20: =-Assumptions!B22 | G20: =-Assumptions!B22 | H20: =-Assumptions!B22 | I20: =-Assumptions!B22 | J20: =-Assumptions!B22 | K20: =-Assumptions!B22 | L20: =-Assumptions!B22 | M20: =-Assumptions!B22 | N20: =SUM(B20:M20)
A21: Software & Tools | B21: =-Assumptions!B23 | C21: =-Assumptions!B23 | D21: =-Assumptions!B23 | E21: =-Assumptions!B23 | F21: =-Assumptions!B23 | G21: =-Assumptions!B23 | H21: =-Assumptions!B23 | I21: =-Assumptions!B23 | J21: =-Assumptions!B23 | K21: =-Assumptions!B23 | L21: =-Assumptions!B23 | M21: =-Assumptions!B23 | N21: =SUM(B21:M21)
A22: Insurance | B22: =-Assumptions!B24 | C22: =-Assumptions!B24 | D22: =-Assumptions!B24 | E22: =-Assumptions!B24 | F22: =-Assumptions!B24 | G22: =-Assumptions!B24 | H22: =-Assumptions!B24 | I22: =-Assumptions!B24 | J22: =-Assumptions!B24 | K22: =-Assumptions!B24 | L22: =-Assumptions!B24 | M22: =-Assumptions!B24 | N22: =SUM(B22:M22)
A23: Miscellaneous | B23: =-Assumptions!B25 | C23: =-Assumptions!B25 | D23: =-Assumptions!B25 | E23: =-Assumptions!B25 | F23: =-Assumptions!B25 | G23: =-Assumptions!B25 | H23: =-Assumptions!B25 | I23: =-Assumptions!B25 | J23: =-Assumptions!B25 | K23: =-Assumptions!B25 | L23: =-Assumptions!B25 | M23: =-Assumptions!B25 | N23: =SUM(B23:M23)
A25: TOTAL OPERATING EXPENSES | B25: =SUM(B15:B23) | C25: =SUM(C15:C23) | D25: =SUM(D15:D23) | E25: =SUM(E15:E23) | F25: =SUM(F15:F23) | G25: =SUM(G15:G23) | H25: =SUM(H15:H23) | I25: =SUM(I15:I23) | ... M25: =SUM(M15:M23) | N25: =SUM(B25:M25)
A27: NET PROFIT / (LOSS) | B27: =B11+B25 | C27: =C11+C25 | D27: =D11+D25 | E27: =E11+E25 | F27: =F11+F25 | G27: =G11+G25 | H27: =H11+H25 | I27: =I11+I25 | ... M27: =M11+M25 | N27: =SUM(B27:M27)
A28: Net Margin % | B28: =IF(B6=0,0,B27/B6) | C28: =IF(C6=0,0,C27/C6) | D28: =IF(D6=0,0,D27/D6) | E28: =IF(E6=0,0,E27/E6) | F28: =IF(F6=0,0,F27/F6) | G28: =IF(G6=0,0,G27/G6) | H28: =IF(H6=0,0,H27/H6) | I28: =IF(I6=0,0,I27/I6) | ... M28: =IF(M6=0,0,M27/M6)

Sheet Cash Flow
A1: 12-MONTH CASH FLOW PROJECTION
B3: Jan | C3: Feb | D3: Mar | E3: Apr | F3: May | G3: Jun | H3: Jul | I3: Aug | J3: Sep | K3: Oct | L3: Nov | M3: Dec
A5: Opening Cash Balance | B5: 0 | C5: =B11 | D5: =C11 | E5: =D11 | F5: =E11 | G5: =F11 | H5: =G11 | I5: =H11 | J5: =I11 | ... M5: =L11
A7: Cash In (Revenue) | B7: ='P&L'!B6 | C7: ='P&L'!C6 | D7: ='P&L'!D6 | E7: ='P&L'!E6 | F7: ='P&L'!F6 | G7: ='P&L'!G6 | H7: ='P&L'!H6 | I7: ='P&L'!I6 | ... M7: ='P&L'!M6
A8: Cash Out (COGS + OpEx) | B8: ='P&L'!B9+'P&L'!B25 | C8: ='P&L'!C9+'P&L'!C25 | D8: ='P&L'!D9+'P&L'!D25 | E8: ='P&L'!E9+'P&L'!E25 | F8: ='P&L'!F9+'P&L'!F25 | G8: ='P&L'!G9+'P&L'!G25 | H8: ='P&L'!H9+'P&L'!H25 | I8: ='P&L'!I9+'P&L'!I25 | ... M8: ='P&L'!M9+'P&L'!M25
A9: Other Cash Out (Capital, Loan Repayment) | B9: 0 | C9: 0 | D9: 0 | E9: 0 | F9: 0 | G9: 0 | H9: 0 | I9: 0 | J9: 0 | K9: 0 | L9: 0 | M9: 0
A10: Net Cash Flow | B10: =B7+B8+B9 | C10: =C7+C8+C9 | D10: =D7+D8+D9 | E10: =E7+E8+E9 | F10: =F7+F8+F9 | G10: =G7+G8+G9 | H10: =H7+H8+H9 | I10: =I7+I8+I9 | ... M10: =M7+M8+M9
A11: Closing Cash Balance | B11: =B5+B10 | C11: =C5+C10 | D11: =D5+D10 | E11: =E5+E10 | F11: =F5+F10 | G11: =G5+G10 | H11: =H5+H10 | I11: =I5+I10 | ... M11: =M5+M10
